sir_hiss/__init__.py
sir_hiss-0.0.4.dist-info/entry_points.txt
sir_hiss-0.0.4.dist-info/WHEEL
sir_hiss-0.0.4.dist-info/METADATA
sir_hiss-0.0.4.dist-info/RECORD
