Metadata-Version: 2.1
Name: sir-hiss
Version: 0.0.4
Summary: Run the relevant tools for a repository
Home-page: https://nest.pijul.com/gwenzek/sir_hiss
Author: gwenzek
Requires-Python: >=3.6,<4.0
Classifier: Programming Language :: Python :: 3
Classifier: Programming Language :: Python :: 3.6
Classifier: Programming Language :: Python :: 3.7
Classifier: Programming Language :: Python :: 3.8
Requires-Dist: func_argparse (>=1.1.1,<2.0.0)
Requires-Dist: toml (>=0.10.0,<0.11.0)
Project-URL: Repository, https://nest.pijul.com/gwenzek/sir_hiss
